[
  {
    "company": "Oyoba",
    "position": "Office Assistant I",
    "location": "Khánh Hải",
    "jobType": "internship",
    "status": "interview",
    "createdBy": "64f76fe25f00336c48274d41",
    "createdAt": "2022-11-06T05:19:21Z"
  },
  {
    "company": "LiveZ",
    "position": "Staff Scientist",
    "location": "Horní Stropnice",
    "jobType": "internship",
    "status": "interview",
    "createdBy": "64f76fe25f00336c48274d41",
    "createdAt": "2023-07-27T13:32:10Z"
  },
  {
    "company": "Wikido",
    "position": "Internal Auditor",
    "location": "Starodub",
    "jobType": "remote",
    "status": "declined",
    "createdBy": "64f76fe25f00336c48274d41",
    "createdAt": "2023-02-09T22:15:01Z"
  },
  {
    "company": "Camimbo",
    "position": "Dental Hygienist",
    "location": "Chengzhong",
    "jobType": "full-time",
    "status": "declined",
    "createdBy": "64f76fe25f00336c48274d41",
    "createdAt": "2022-11-15T18:04:00Z"
  },
  {
    "company": "Babbleset",
    "position": "Electrical Engineer",
    "location": "Zhangjiayuan",
    "jobType": "full-time",
    "status": "pending",
    "createdBy": "64f76fe25f00336c48274d41",
    "createdAt": "2023-05-01T18:15:44Z"
  },
  {
    "company": "Aivee",
    "position": "Project Manager",
    "location": "Perre",
    "jobType": "remote",
    "status": "interview",
    "createdBy": "64f76fe25f00336c48274d41",
    "createdAt": "2023-01-13T23:24:53Z"
  },
  {
    "company": "Reallinks",
    "position": "Nurse Practicioner",
    "location": "Macaé",
    "jobType": "part-time",
    "status": "pending",
    "createdBy": "64f76fe25f00336c48274d41",
    "createdAt": "2023-04-15T16:38:47Z"
  },
  {
    "company": "Skipfire",
    "position": "VP Product Management",
    "location": "Huagai",
    "jobType": "full-time",
    "status": "pending",
    "createdBy": "64f76fe25f00336c48274d41",
    "createdAt": "2023-09-28T07:43:40Z"
  },
  {
    "company": "Jayo",
    "position": "Professor",
    "location": "Kičevo",
    "jobType": "internship",
    "status": "interview",
    "createdBy": "64f76fe25f00336c48274d41",
    "createdAt": "2023-04-27T07:43:40Z"
  },
  {
    "company": "Rhyzio",
    "position": "Accounting Assistant I",
    "location": "Maubin",
    "jobType": "full-time",
    "status": "interview",
    "createdBy": "64f76fe25f00336c48274d41",
    "createdAt": "2023-04-02T03:27:52Z"
  },
  {
    "company": "Photobug",
    "position": "Research Associate",
    "location": "Jingguan",
    "jobType": "remote",
    "status": "interview",
    "createdBy": "64f76fe25f00336c48274d41",
    "createdAt": "2023-10-13T04:12:26Z"
  },
  {
    "company": "Realpoint",
    "position": "Health Coach II",
    "location": "Quibdó",
    "jobType": "remote",
    "status": "pending",
    "createdBy": "64f76fe25f00336c48274d41",
    "createdAt": "2023-02-20T10:51:40Z"
  },
  {
    "company": "Brainsphere",
    "position": "Junior Executive",
    "location": "Clorinda",
    "jobType": "internship",
    "status": "declined",
    "createdBy": "64f76fe25f00336c48274d41",
    "createdAt": "2023-05-15T19:01:18Z"
  },
  {
    "company": "Twimbo",
    "position": "Human Resources Assistant II",
    "location": "Nizhnepavlovka",
    "jobType": "remote",
    "status": "interview",
    "createdBy": "64f76fe25f00336c48274d41",
    "createdAt": "2022-12-26T02:06:20Z"
  },
  {
    "company": "Gabvine",
    "position": "Tax Accountant",
    "location": "Banjar Ponggang",
    "jobType": "internship",
    "status": "declined",
    "createdBy": "64f76fe25f00336c48274d41",
    "createdAt": "2023-01-26T15:34:08Z"
  },
  {
    "company": "Mycat",
    "position": "Professor",
    "location": "Zhaotong",
    "jobType": "internship",
    "status": "pending",
    "createdBy": "64f76fe25f00336c48274d41",
    "createdAt": "2023-09-04T13:49:32Z"
  },
  {
    "company": "Realbridge",
    "position": "VP Accounting",
    "location": "Raciążek",
    "jobType": "internship",
    "status": "pending",
    "createdBy": "64f76fe25f00336c48274d41",
    "createdAt": "2023-09-09T10:04:32Z"
  },
  {
    "company": "Feedspan",
    "position": "Geological Engineer",
    "location": "Sheshan",
    "jobType": "full-time",
    "status": "pending",
    "createdBy": "64f76fe25f00336c48274d41",
    "createdAt": "2023-09-09T12:15:11Z"
  },
  {
    "company": "Jabberstorm",
    "position": "Pharmacist",
    "location": "Sobienie Jeziory",
    "jobType": "internship",
    "status": "interview",
    "createdBy": "64f76fe25f00336c48274d41",
    "createdAt": "2023-05-21T09:27:54Z"
  },
  {
    "company": "Plajo",
    "position": "Mechanical Systems Engineer",
    "location": "Březová",
    "jobType": "remote",
    "status": "pending",
    "createdBy": "64f76fe25f00336c48274d41",
    "createdAt": "2023-09-27T20:31:27Z"
  },
  {
    "company": "Vinder",
    "position": "Analog Circuit Design manager",
    "location": "Serra de Santa Marinha",
    "jobType": "internship",
    "status": "pending",
    "createdBy": "64f76fe25f00336c48274d41",
    "createdAt": "2023-02-18T18:53:20Z"
  },
  {
    "company": "Tambee",
    "position": "Dental Hygienist",
    "location": "Cashel",
    "jobType": "remote",
    "status": "pending",
    "createdBy": "64f76fe25f00336c48274d41",
    "createdAt": "2023-07-21T21:45:47Z"
  },
  {
    "company": "Kayveo",
    "position": "Director of Sales",
    "location": "Atamanovka",
    "jobType": "full-time",
    "status": "declined",
    "createdBy": "64f76fe25f00336c48274d41",
    "createdAt": "2023-05-31T06:54:46Z"
  },
  {
    "company": "Rhynyx",
    "position": "GIS Technical Architect",
    "location": "Shreveport",
    "jobType": "remote",
    "status": "pending",
    "createdBy": "64f76fe25f00336c48274d41",
    "createdAt": "2022-12-14T22:32:26Z"
  },
  {
    "company": "Zava",
    "position": "Marketing Manager",
    "location": "Jojoima",
    "jobType": "internship",
    "status": "interview",
    "createdBy": "64f76fe25f00336c48274d41",
    "createdAt": "2023-04-18T22:21:13Z"
  },
  {
    "company": "Jaxspan",
    "position": "Biostatistician III",
    "location": "Saarbrücken",
    "jobType": "full-time",
    "status": "interview",
    "createdBy": "64f76fe25f00336c48274d41",
    "createdAt": "2022-12-21T08:53:43Z"
  },
  {
    "company": "Centidel",
    "position": "Marketing Assistant",
    "location": "Al Jahrā’",
    "jobType": "full-time",
    "status": "pending",
    "createdBy": "64f76fe25f00336c48274d41",
    "createdAt": "2023-09-12T07:01:15Z"
  },
  {
    "company": "Aivee",
    "position": "Senior Editor",
    "location": "Babiak",
    "jobType": "part-time",
    "status": "pending",
    "createdBy": "64f76fe25f00336c48274d41",
    "createdAt": "2023-01-23T00:09:00Z"
  },
  {
    "company": "Zoombox",
    "position": "Internal Auditor",
    "location": "Valleymount",
    "jobType": "remote",
    "status": "declined",
    "createdBy": "64f76fe25f00336c48274d41",
    "createdAt": "2023-03-17T03:28:07Z"
  },
  {
    "company": "Gabtype",
    "position": "Safety Technician I",
    "location": "Luocheng",
    "jobType": "full-time",
    "status": "interview",
    "createdBy": "64f76fe25f00336c48274d41",
    "createdAt": "2023-10-19T02:48:02Z"
  },
  {
    "company": "Meemm",
    "position": "Senior Editor",
    "location": "Mezinovskiy",
    "jobType": "internship",
    "status": "interview",
    "createdBy": "64f76fe25f00336c48274d41",
    "createdAt": "2023-04-02T11:59:29Z"
  },
  {
    "company": "Skaboo",
    "position": "Environmental Tech",
    "location": "Suresnes",
    "jobType": "part-time",
    "status": "pending",
    "createdBy": "64f76fe25f00336c48274d41",
    "createdAt": "2023-09-23T08:07:56Z"
  },
  {
    "company": "Dazzlesphere",
    "position": "Compensation Analyst",
    "location": "Hangkou",
    "jobType": "remote",
    "status": "declined",
    "createdBy": "64f76fe25f00336c48274d41",
    "createdAt": "2023-03-25T02:48:43Z"
  },
  {
    "company": "Realmix",
    "position": "Internal Auditor",
    "location": "Wangmang",
    "jobType": "part-time",
    "status": "pending",
    "createdBy": "64f76fe25f00336c48274d41",
    "createdAt": "2023-02-26T08:21:34Z"
  },
  {
    "company": "Izio",
    "position": "Payment Adjustment Coordinator",
    "location": "Pagersari",
    "jobType": "full-time",
    "status": "pending",
    "createdBy": "64f76fe25f00336c48274d41",
    "createdAt": "2022-10-26T14:58:01Z"
  },
  {
    "company": "Divape",
    "position": "Occupational Therapist",
    "location": "Lintan Chengguanzhen",
    "jobType": "internship",
    "status": "pending",
    "createdBy": "64f76fe25f00336c48274d41",
    "createdAt": "2023-04-24T12:52:32Z"
  },
  {
    "company": "Skyble",
    "position": "Office Assistant III",
    "location": "Rabat",
    "jobType": "remote",
    "status": "pending",
    "createdBy": "64f76fe25f00336c48274d41",
    "createdAt": "2023-10-12T01:12:01Z"
  },
  {
    "company": "Demimbu",
    "position": "Clinical Specialist",
    "location": "Krajan Kulon",
    "jobType": "remote",
    "status": "pending",
    "createdBy": "64f76fe25f00336c48274d41",
    "createdAt": "2023-06-05T05:23:23Z"
  },
  {
    "company": "Oodoo",
    "position": "Research Associate",
    "location": "Valledupar",
    "jobType": "remote",
    "status": "interview",
    "createdBy": "64f76fe25f00336c48274d41",
    "createdAt": "2023-04-23T10:32:11Z"
  },
  {
    "company": "Divanoodle",
    "position": "Engineer II",
    "location": "Orlu",
    "jobType": "remote",
    "status": "declined",
    "createdBy": "64f76fe25f00336c48274d41",
    "createdAt": "2023-03-01T13:18:14Z"
  },
  {
    "company": "Vinder",
    "position": "Product Engineer",
    "location": "Prakhon Chai",
    "jobType": "full-time",
    "status": "pending",
    "createdBy": "64f76fe25f00336c48274d41",
    "createdAt": "2023-03-15T00:51:17Z"
  },
  {
    "company": "Roombo",
    "position": "Geological Engineer",
    "location": "Hammarö",
    "jobType": "full-time",
    "status": "declined",
    "createdBy": "64f76fe25f00336c48274d41",
    "createdAt": "2022-12-17T18:44:44Z"
  },
  {
    "company": "Meedoo",
    "position": "Dental Hygienist",
    "location": "Tengah",
    "jobType": "internship",
    "status": "pending",
    "createdBy": "64f76fe25f00336c48274d41",
    "createdAt": "2023-10-17T19:49:16Z"
  },
  {
    "company": "Vitz",
    "position": "Senior Editor",
    "location": "Lubuk Sikaping",
    "jobType": "part-time",
    "status": "declined",
    "createdBy": "64f76fe25f00336c48274d41",
    "createdAt": "2022-11-11T16:48:12Z"
  },
  {
    "company": "Demivee",
    "position": "Nurse",
    "location": "Shumerlya",
    "jobType": "internship",
    "status": "interview",
    "createdBy": "64f76fe25f00336c48274d41",
    "createdAt": "2023-03-31T09:22:51Z"
  },
  {
    "company": "Fatz",
    "position": "Automation Specialist III",
    "location": "Paraíso de Chabasquén",
    "jobType": "internship",
    "status": "pending",
    "createdBy": "64f76fe25f00336c48274d41",
    "createdAt": "2022-12-30T21:08:05Z"
  },
  {
    "company": "Skinte",
    "position": "Chemical Engineer",
    "location": "Santa Cruz",
    "jobType": "part-time",
    "status": "pending",
    "createdBy": "64f76fe25f00336c48274d41",
    "createdAt": "2023-05-10T20:15:31Z"
  },
  {
    "company": "Twitterbridge",
    "position": "Director of Sales",
    "location": "Shanban",
    "jobType": "remote",
    "status": "pending",
    "createdBy": "64f76fe25f00336c48274d41",
    "createdAt": "2023-05-27T08:25:43Z"
  },
  {
    "company": "Zoomlounge",
    "position": "Electrical Engineer",
    "location": "Żarki-Letnisko",
    "jobType": "full-time",
    "status": "declined",
    "createdBy": "64f76fe25f00336c48274d41",
    "createdAt": "2023-08-24T04:48:27Z"
  },
  {
    "company": "Innojam",
    "position": "Clinical Specialist",
    "location": "Tawaran",
    "jobType": "remote",
    "status": "interview",
    "createdBy": "64f76fe25f00336c48274d41",
    "createdAt": "2023-06-26T01:56:52Z"
  },
  {
    "company": "Jabbersphere",
    "position": "Software Consultant",
    "location": "Manalad",
    "jobType": "internship",
    "status": "interview",
    "createdBy": "64f76fe25f00336c48274d41",
    "createdAt": "2023-08-26T05:46:01Z"
  },
  {
    "company": "Meejo",
    "position": "Physical Therapy Assistant",
    "location": "Baitu",
    "jobType": "remote",
    "status": "declined",
    "createdBy": "64f76fe25f00336c48274d41",
    "createdAt": "2023-10-12T01:14:41Z"
  },
  {
    "company": "Dabvine",
    "position": "Assistant Media Planner",
    "location": "La Tinguiña",
    "jobType": "internship",
    "status": "pending",
    "createdBy": "64f76fe25f00336c48274d41",
    "createdAt": "2022-12-29T07:23:45Z"
  },
  {
    "company": "Browsebug",
    "position": "Engineer I",
    "location": "Paamiut",
    "jobType": "part-time",
    "status": "declined",
    "createdBy": "64f76fe25f00336c48274d41",
    "createdAt": "2023-01-16T16:04:40Z"
  },
  {
    "company": "Edgeify",
    "position": "VP Sales",
    "location": "Malunda",
    "jobType": "full-time",
    "status": "interview",
    "createdBy": "64f76fe25f00336c48274d41",
    "createdAt": "2023-04-15T20:04:48Z"
  },
  {
    "company": "Feedbug",
    "position": "Registered Nurse",
    "location": "Myitkyina",
    "jobType": "internship",
    "status": "declined",
    "createdBy": "64f76fe25f00336c48274d41",
    "createdAt": "2023-08-22T09:25:23Z"
  },
  {
    "company": "Gigaclub",
    "position": "Professor",
    "location": "Jesús María",
    "jobType": "full-time",
    "status": "pending",
    "createdBy": "64f76fe25f00336c48274d41",
    "createdAt": "2022-11-23T02:50:09Z"
  },
  {
    "company": "Myworks",
    "position": "Electrical Engineer",
    "location": "Mengla",
    "jobType": "full-time",
    "status": "declined",
    "createdBy": "64f76fe25f00336c48274d41",
    "createdAt": "2023-10-13T10:33:36Z"
  },
  {
    "company": "Eamia",
    "position": "Desktop Support Technician",
    "location": "Iłowa",
    "jobType": "internship",
    "status": "declined",
    "createdBy": "64f76fe25f00336c48274d41",
    "createdAt": "2023-01-26T15:56:27Z"
  },
  {
    "company": "Meejo",
    "position": "Professor",
    "location": "Peace River",
    "jobType": "part-time",
    "status": "pending",
    "createdBy": "64f76fe25f00336c48274d41",
    "createdAt": "2022-10-25T14:56:08Z"
  },
  {
    "company": "Shuffletag",
    "position": "VP Product Management",
    "location": "Svay Rieng",
    "jobType": "internship",
    "status": "pending",
    "createdBy": "64f76fe25f00336c48274d41",
    "createdAt": "2023-10-14T18:11:55Z"
  },
  {
    "company": "Kwinu",
    "position": "Marketing Manager",
    "location": "Senanga",
    "jobType": "remote",
    "status": "interview",
    "createdBy": "64f76fe25f00336c48274d41",
    "createdAt": "2022-12-07T08:36:06Z"
  },
  {
    "company": "Meemm",
    "position": "Structural Engineer",
    "location": "Puunage",
    "jobType": "remote",
    "status": "interview",
    "createdBy": "64f76fe25f00336c48274d41",
    "createdAt": "2023-01-31T14:38:48Z"
  },
  {
    "company": "DabZ",
    "position": "Senior Editor",
    "location": "Yangju",
    "jobType": "remote",
    "status": "declined",
    "createdBy": "64f76fe25f00336c48274d41",
    "createdAt": "2023-03-01T02:24:28Z"
  },
  {
    "company": "Brainbox",
    "position": "Structural Engineer",
    "location": "Toyama-shi",
    "jobType": "internship",
    "status": "interview",
    "createdBy": "64f76fe25f00336c48274d41",
    "createdAt": "2023-08-25T03:13:09Z"
  },
  {
    "company": "Babblestorm",
    "position": "Account Executive",
    "location": "Arlington",
    "jobType": "remote",
    "status": "pending",
    "createdBy": "64f76fe25f00336c48274d41",
    "createdAt": "2023-06-21T06:08:10Z"
  },
  {
    "company": "Skivee",
    "position": "Research Assistant III",
    "location": "Baiyang",
    "jobType": "internship",
    "status": "pending",
    "createdBy": "64f76fe25f00336c48274d41",
    "createdAt": "2023-01-08T14:34:37Z"
  },
  {
    "company": "Jabbercube",
    "position": "Computer Systems Analyst II",
    "location": "Berlin",
    "jobType": "full-time",
    "status": "interview",
    "createdBy": "64f76fe25f00336c48274d41",
    "createdAt": "2023-08-24T15:01:39Z"
  },
  {
    "company": "Tazzy",
    "position": "Operator",
    "location": "Arrabal",
    "jobType": "remote",
    "status": "interview",
    "createdBy": "64f76fe25f00336c48274d41",
    "createdAt": "2023-06-27T16:11:13Z"
  },
  {
    "company": "Dabshots",
    "position": "Software Test Engineer I",
    "location": "Haokou",
    "jobType": "part-time",
    "status": "pending",
    "createdBy": "64f76fe25f00336c48274d41",
    "createdAt": "2023-09-07T01:10:32Z"
  },
  {
    "company": "Twitterlist",
    "position": "Database Administrator II",
    "location": "Tullamore",
    "jobType": "part-time",
    "status": "interview",
    "createdBy": "64f76fe25f00336c48274d41",
    "createdAt": "2023-04-07T06:16:48Z"
  },
  {
    "company": "Youspan",
    "position": "Product Engineer",
    "location": "Al Bawīţī",
    "jobType": "part-time",
    "status": "interview",
    "createdBy": "64f76fe25f00336c48274d41",
    "createdAt": "2023-05-03T02:32:42Z"
  },
  {
    "company": "Zoozzy",
    "position": "Web Designer I",
    "location": "Kedungreja",
    "jobType": "full-time",
    "status": "pending",
    "createdBy": "64f76fe25f00336c48274d41",
    "createdAt": "2023-04-28T14:07:25Z"
  },
  {
    "company": "Avamba",
    "position": "Information Systems Manager",
    "location": "Vilque",
    "jobType": "part-time",
    "status": "interview",
    "createdBy": "64f76fe25f00336c48274d41",
    "createdAt": "2023-03-16T05:02:34Z"
  },
  {
    "company": "Dabvine",
    "position": "Health Coach II",
    "location": "Lobitos",
    "jobType": "part-time",
    "status": "interview",
    "createdBy": "64f76fe25f00336c48274d41",
    "createdAt": "2022-11-18T05:22:13Z"
  }
]
